pyaecal/__init__.py
pyaecal/axis.py
pyaecal/cdf.py
pyaecal/curve.py
pyaecal/dcm.py
pyaecal/emotor.py
pyaecal/engine.py
pyaecal/extract.py
pyaecal/function.py
pyaecal/gearbox.py
pyaecal/generator.py
pyaecal/log.py
pyaecal/map.py
pyaecal/parser.py
pyaecal/resistance.py
pyaecal/shift.py
pyaecal/trigger.py
pyaecal/value.py
pyaecal/vbo.py
pyaecal/vehicle.py
pyaecal/watchdog.py
pyaecal-0.30.dist-info/licenses/LICENSE.txt
pyaecal-0.30.dist-info/METADATA
pyaecal-0.30.dist-info/WHEEL
pyaecal-0.30.dist-info/top_level.txt
pyaecal-0.30.dist-info/RECORD
