Metadata-Version: 2.4
Name: pyaecal
Version: 0.30
Summary: Automtotive Electronic Calibration
Home-page: https://gitlab.com/hexamake/python/pyaecal.git
Author: Jerome Douay
Author-email: jerome@hexamake.com
License: MIT
Project-URL: Documentation, https://pyscaffold.org/
Platform: any
Classifier: Development Status :: 4 - Beta
Classifier: Programming Language :: Python
License-File: LICENSE.txt
Requires-Dist: importlib-metadata; python_version < "3.8"
Provides-Extra: testing
Requires-Dist: setuptools; extra == "testing"
Requires-Dist: pytest; extra == "testing"
Requires-Dist: pytest-cov; extra == "testing"
Dynamic: license-file
